EDS.py
i2cdriver.py
i2cdriver-1.0.6.dist-info/METADATA
i2cdriver-1.0.6.dist-info/WHEEL
i2cdriver-1.0.6.dist-info/entry_points.txt
i2cdriver-1.0.6.dist-info/top_level.txt
i2cdriver-1.0.6.dist-info/RECORD
